.travis.yml
AUTHORS
LICENSE
MANIFEST.in
README.rst
dev-requirements.txt
flake8_quotes.py
setup.cfg
setup.py
tox.ini
flake8_quotes2.egg-info/PKG-INFO
flake8_quotes2.egg-info/SOURCES.txt
flake8_quotes2.egg-info/dependency_links.txt
flake8_quotes2.egg-info/entry_points.txt
flake8_quotes2.egg-info/pbr.json
flake8_quotes2.egg-info/requires.txt
flake8_quotes2.egg-info/top_level.txt
tests/test_checker.py